<Page xmlns="http://schemas.nativescript.org/tns.xsd" xmlns:ui="@nativescript-community/ui-constraintlayout" navigatingTo="navigatingTo" class="page">
  <Page.actionBar>
    <ActionBar title="layout-direction" icon="" class="action-bar">
    </ActionBar>
  </Page.actionBar>
  <StackLayout padding="30">
    <Label text="LTR" marginBottom="16"/>
    <ui:ConstraintLayout direction="ltr">
      <Button id="button1" text="startToStartOf" width="150" height="150" startToStartOf="parent" topToTopOf="parent" bottomToBottomOf="parent" backgroundColor="red"/>
      <Button id="button2" text="endToEndOf" width="150" height="150" endToEndOf="parent" topToTopOf="parent" bottomToBottomOf="parent" backgroundColor="yellow"/>
    </ui:ConstraintLayout>
    <Label text="RTL" marginTop="32" marginBottom="16"/>
    <ui:ConstraintLayout direction="rtl">
      <Button id="button1" text="startToStartOf" width="150" height="150" startToStartOf="parent" topToTopOf="parent" bottomToBottomOf="parent" backgroundColor="red"/>
      <Button id="button2" text="endToEndOf" width="150" height="150" endToEndOf="parent" topToTopOf="parent" bottomToBottomOf="parent" backgroundColor="yellow"/>
    </ui:ConstraintLayout>
  </StackLayout>
</Page>